{
  "Id": 298570,
  "ImdbId": "tt4120078",
  "Title": "Little Azkals",
  "OriginalTitle": "Little Azkals",
  "Status": "Released",
  "Overview": "a film by Baby Ruth Villarama.",
  "PosterPath": "/iJQaSgyhOCoAE20PNuwMLEiSPRM.jpg",
  "Genres": [
    {
      "Id": 99,
      "Name": "Documentary"
    }
  ],
  "ReleaseDate": "2014-10-25T00:00:00",
  "Runtime": 0,
  "Popularity": 0.530942932586962,
  "ProductionCompanies": [],
  "ProductionCountries": [],
  "SpokenLanguages": [
    {
      "Iso_639_1": "en",
      "Name": "English"
    },
    {
      "Iso_639_1": "tl"
    }
  ],
  "AlternativeTitles": {
    "Id": 298570,
    "Titles": []
  },
  "Releases": {
    "Id": 298570,
    "Countries": [
      {
        "Iso_3166_1": "PH",
        "ReleaseDate": "2014-10-25T00:00:00"
      }
    ]
  },
  "Credits": {
    "Id": 298570,
    "Cast": [],
    "Crew": [
      {
        "Id": 1308834,
        "Name": "Baby Ruth Villarama",
        "Department": "Directing",
        "Job": "Director"
      }
    ]
  },
  "Images": {
    "Backdrops": [],
    "Posters": [
      {
        "FilePath": "/iJQaSgyhOCoAE20PNuwMLEiSPRM.jpg",
        "Width": 500,
        "Height": 750,
        "AspectRatio": 0.666666666666667
      },
      {
        "FilePath": "/dvXhytczQ2DeeAsyoAlhee8HmgQ.jpg",
        "Width": 530,
        "Height": 790,
        "AspectRatio": 0.670886075949367
      }
    ]
  },
  "Keywords": {
    "Id": 298570,
    "Keywords": []
  },
  "Trailers": {
    "Id": 298570,
    "Quicktime": [],
    "Youtube": []
  },
  "Translations": {
    "Id": 298570,
    "Translations": [
      {
        "Iso_639_1": "en",
        "Name": "English",
        "EnglishName": "English"
      }
    ]
  }
}