{
  "Id": 271983,
  "Title": "Entre Abelhas",
  "OriginalTitle": "Entre Abelhas",
  "Status": "Released",
  "Genres": [],
  "ReleaseDate": "2014-10-23T00:00:00",
  "Popularity": 0.220395086527411,
  "ProductionCompanies": [],
  "ProductionCountries": [
    {
      "Iso_3166_1": "BR",
      "Name": "Brazil"
    }
  ],
  "SpokenLanguages": [
    {
      "Iso_639_1": "pt",
      "Name": "Português"
    }
  ],
  "AlternativeTitles": {
    "Id": 271983,
    "Titles": []
  },
  "Releases": {
    "Id": 271983,
    "Countries": [
      {
        "Iso_3166_1": "BR",
        "ReleaseDate": "2014-10-23T00:00:00"
      }
    ]
  },
  "Credits": {
    "Id": 271983,
    "Cast": [
      {
        "Id": 1095855,
        "Name": "Fábio Porchat",
        "Order": 1,
        "ProfilePath": "/cGxlCSYXRiXu2Z4vDkSGU5yhBlp.jpg"
      },
      {
        "Id": 1278433,
        "Name": "Marcos Veras",
        "Order": 2,
        "CastId": 1
      },
      {
        "Id": 967080,
        "Name": "Marcelo Valle",
        "Order": 3,
        "CastId": 2
      },
      {
        "Id": 1324365,
        "Name": "Leticia Lima",
        "Order": 4,
        "CastId": 3
      },
      {
        "Id": 1324366,
        "Name": "Luis Lobianco",
        "Order": 5,
        "CastId": 4
      }
    ],
    "Crew": [
      {
        "Id": 1324367,
        "Name": "Ian SBF",
        "Department": "Directing",
        "Job": "Director"
      }
    ]
  },
  "Images": {
    "Backdrops": [],
    "Posters": []
  },
  "Keywords": {
    "Id": 271983,
    "Keywords": []
  },
  "Trailers": {
    "Id": 271983,
    "Quicktime": [],
    "Youtube": []
  },
  "Translations": {
    "Id": 271983,
    "Translations": [
      {
        "Iso_639_1": "pt",
        "Name": "Português",
        "EnglishName": "Portuguese"
      }
    ]
  }
}