{
  "Id": 300603,
  "Title": "Plop en de Brandweer Kabouter",
  "OriginalTitle": "Plop en de Brandweer Kabouter",
  "Status": "Released",
  "PosterPath": "/jeJQHZDPL4Breo92SlragmRQ368.jpg",
  "Genres": [
    {
      "Id": 10751,
      "Name": "Family"
    }
  ],
  "ReleaseDate": "2014-10-10T00:00:00",
  "ProductionCompanies": [
    {
      "Name": "Studio 100",
      "Id": 25894
    }
  ],
  "ProductionCountries": [
    {
      "Iso_3166_1": "BE",
      "Name": "Belgium"
    }
  ],
  "SpokenLanguages": [],
  "AlternativeTitles": {
    "Id": 300603,
    "Titles": []
  },
  "Releases": {
    "Id": 300603,
    "Countries": [
      {
        "Iso_3166_1": "BE",
        "ReleaseDate": "2014-10-10T00:00:00"
      }
    ]
  },
  "Credits": {
    "Id": 300603,
    "Cast": [
      {
        "Id": 116731,
        "Name": "Walter de Donder",
        "Character": "Plop",
        "Order": 1,
        "ProfilePath": "/75ABynlbUbKYFSB5oQvees6yrhu.jpg"
      },
      {
        "Id": 146579,
        "Name": "Chris Cauwenberghs",
        "Character": "Lui",
        "Order": 2,
        "CastId": 1,
        "ProfilePath": "/2KFywFrKueS0CwdeByKCUdcVCNW.jpg"
      },
      {
        "Id": 116733,
        "Name": "Aimé Anthoni",
        "Character": "Klus",
        "Order": 3,
        "CastId": 2
      },
      {
        "Id": 116732,
        "Name": "Agnes De Nul",
        "Character": "Kwebbel",
        "Order": 4,
        "CastId": 3
      }
    ],
    "Crew": []
  },
  "Images": {
    "Backdrops": [],
    "Posters": [
      {
        "FilePath": "/jeJQHZDPL4Breo92SlragmRQ368.jpg",
        "Width": 500,
        "Height": 750,
        "AspectRatio": 0.666666666666667
      }
    ]
  },
  "Keywords": {
    "Id": 300603,
    "Keywords": []
  },
  "Trailers": {
    "Id": 300603,
    "Quicktime": [],
    "Youtube": []
  },
  "Translations": {
    "Id": 300603,
    "Translations": [
      {
        "Iso_639_1": "nl",
        "Name": "Nederlands",
        "EnglishName": "Dutch"
      }
    ]
  }
}