{
  "Id": 299400,
  "ImdbId": "tt3922810",
  "Title": "Santa Claws",
  "OriginalTitle": "Santa Claws",
  "Status": "Released",
  "Overview": "Santa is allergic to cats",
  "Genres": [
    {
      "Id": 10751,
      "Name": "Family"
    }
  ],
  "ReleaseDate": "2014-11-04T00:00:00",
  "Runtime": 0,
  "Popularity": 2.0053244325,
  "ProductionCompanies": [],
  "ProductionCountries": [],
  "SpokenLanguages": [],
  "AlternativeTitles": {
    "Id": 299400,
    "Titles": []
  },
  "Releases": {
    "Id": 299400,
    "Countries": [
      {
        "Iso_3166_1": "US",
        "ReleaseDate": "2014-11-04T00:00:00"
      }
    ]
  },
  "Credits": {
    "Id": 299400,
    "Cast": [],
    "Crew": []
  },
  "Images": {
    "Backdrops": [],
    "Posters": []
  },
  "Keywords": {
    "Id": 299400,
    "Keywords": [
      {
        "Id": 40789,
        "Name": " christmas"
      },
      {
        "Id": 207104,
        "Name": "cats"
      }
    ]
  },
  "Trailers": {
    "Id": 299400,
    "Quicktime": [],
    "Youtube": [
      {
        "Name": "Trailer 1",
        "Size": "HD",
        "Source": "4a_aAoGwevU"
      }
    ]
  },
  "Translations": {
    "Id": 299400,
    "Translations": [
      {
        "Iso_639_1": "en",
        "Name": "English",
        "EnglishName": "English"
      }
    ]
  }
}