{
  "Id": 241207,
  "ImdbId": "tt2124959",
  "Title": "The Red Robin",
  "OriginalTitle": "The Red Robin",
  "Status": "Released",
  "Overview": "A family reunion goes awry when the oldest son makes the accusation that his dying father, a famed psychiatrist who also did work for the CIA, adopted his children for the purposes of psychological experimentation.",
  "PosterPath": "/rKTZkQPeOn5FwoMhzePomasgig.jpg",
  "Genres": [
    {
      "Id": 18,
      "Name": "Drama"
    },
    {
      "Id": 53,
      "Name": "Thriller"
    }
  ],
  "ReleaseDate": "2014-10-09T00:00:00",
  "Runtime": 0,
  "Popularity": 0.243664352328843,
  "ProductionCompanies": [
    {
      "Name": "Rowish Entertainment",
      "Id": 18598
    },
    {
      "Name": "Rowish Productions",
      "Id": 18599
    },
    {
      "Name": "mKarma Productions",
      "Id": 18600
    }
  ],
  "ProductionCountries": [
    {
      "Iso_3166_1": "US",
      "Name": "United States of America"
    }
  ],
  "SpokenLanguages": [],
  "AlternativeTitles": {
    "Id": 241207,
    "Titles": []
  },
  "Releases": {
    "Id": 241207,
    "Countries": [
      {
        "Iso_3166_1": "US",
        "ReleaseDate": "2014-10-09T00:00:00"
      }
    ]
  },
  "Credits": {
    "Id": 241207,
    "Cast": [
      {
        "Id": 6167,
        "Name": "Judd Hirsch",
        "Character": "Dr. Nathaniel Shellner",
        "CastId": 1,
        "ProfilePath": "/5KXEekVgmWQkhvtOd7BtOnQBSQh.jpg"
      },
      {
        "Id": 142192,
        "Name": "Ryan O'Nan",
        "Character": "Tommy Shellner",
        "Order": 1,
        "CastId": 2,
        "ProfilePath": "/sXZOZiVoAm4kKR437AoLECfxBNi.jpg"
      },
      {
        "Id": 164380,
        "Name": "C.S. Lee",
        "Character": "Harry",
        "Order": 2,
        "CastId": 13,
        "ProfilePath": "/gFceFYo2rGpSIjAJTTbpKLoc5mn.jpg"
      },
      {
        "Id": 109151,
        "Name": "Jaime Ray Newman",
        "Character": "Julie",
        "Order": 3,
        "CastId": 4,
        "ProfilePath": "/4jh45lXQPqvuiYy1Fzbk5fJGVr.jpg"
      },
      {
        "Id": 1213094,
        "Name": "Caroline Lagerfelt",
        "Character": "Lillian",
        "Order": 4,
        "CastId": 5,
        "ProfilePath": "/vSCDnlVfJvWWAgst4r02EiXF80r.jpg"
      },
      {
        "Id": 159879,
        "Name": "Joseph Lyle Taylor",
        "Character": "Leonard Shellner",
        "Order": 5,
        "CastId": 6,
        "ProfilePath": "/9CIOs5oFBZMpIczFK0qTRTbeVlO.jpg"
      },
      {
        "Id": 20481,
        "Name": "Jake Miller",
        "Character": "Sasha",
        "Order": 6,
        "CastId": 7
      },
      {
        "Id": 212132,
        "Name": "Lily Pilblad",
        "Character": "Sylvia",
        "Order": 7,
        "CastId": 8,
        "ProfilePath": "/6durTaPRgeGs1eShrvECJgiescC.jpg"
      },
      {
        "Id": 133384,
        "Name": "Dennis Flanagan",
        "Character": "Sergeant Joseph Robbins",
        "Order": 8,
        "CastId": 9
      },
      {
        "Id": 67515,
        "Name": "Marilyn Chris",
        "Character": "Elizabeth Robbins",
        "Order": 9,
        "CastId": 10
      },
      {
        "Id": 1276344,
        "Name": "Dana Konner",
        "Order": 10,
        "CastId": 11
      }
    ],
    "Crew": [
      {
        "Id": 1276345,
        "Name": "Michael Z. Wechsler",
        "Department": "Directing",
        "Job": "Director"
      }
    ]
  },
  "Images": {
    "Backdrops": [],
    "Posters": [
      {
        "FilePath": "/rKTZkQPeOn5FwoMhzePomasgig.jpg",
        "Width": 771,
        "Height": 1030,
        "AspectRatio": 0.748543689320388
      }
    ]
  },
  "Keywords": {
    "Id": 241207,
    "Keywords": []
  },
  "Trailers": {
    "Id": 241207,
    "Quicktime": [],
    "Youtube": []
  },
  "Translations": {
    "Id": 241207,
    "Translations": [
      {
        "Iso_639_1": "en",
        "Name": "English",
        "EnglishName": "English"
      }
    ]
  }
}